LICENSE
MANIFEST.in
setup.py
docs/HISTORY.rst
docs/README.rst
pkg/css/dev/darkmode.css
pkg/css/dev/emerald.css
pkg/css/dev/lightmode.css
pkg/css/dev/myams.css
pkg/css/ext/bootstrap-colorpicker.css
pkg/css/ext/bootstrap-colorpicker.min.css
pkg/css/ext/bootstrap-treeview.css
pkg/css/ext/bootstrap-treeview.min.css
pkg/css/ext/bootstrap.css
pkg/css/ext/bootstrap.min.css
pkg/css/ext/dropzone.css
pkg/css/ext/dropzone.min.css
pkg/css/ext/fontawesome-all.css
pkg/css/ext/fontawesome-all.min.css
pkg/css/ext/fontawesome.css
pkg/css/ext/fontawesome.min.css
pkg/css/ext/imgareaselect-animated.css
pkg/css/ext/imgareaselect-animated.min.css
pkg/css/ext/imgareaselect-default.css
pkg/css/ext/imgareaselect-default.min.css
pkg/css/ext/imgareaselect-deprecated.css
pkg/css/ext/imgareaselect-deprecated.min.css
pkg/css/ext/jquery-ui.structure.css
pkg/css/ext/jquery-ui.structure.min.css
pkg/css/ext/tempusdominus-bootstrap4.css
pkg/css/ext/tempusdominus-bootstrap4.min.css
pkg/css/ext/datatables/autoFill.bootstrap4.css
pkg/css/ext/datatables/autoFill.bootstrap4.min.css
pkg/css/ext/datatables/buttons.bootstrap4.css
pkg/css/ext/datatables/buttons.bootstrap4.min.css
pkg/css/ext/datatables/colReorder.bootstrap4.css
pkg/css/ext/datatables/colReorder.bootstrap4.min.css
pkg/css/ext/datatables/dataTables.bootstrap4.css
pkg/css/ext/datatables/dataTables.bootstrap4.min.css
pkg/css/ext/datatables/dataTables.css
pkg/css/ext/datatables/dataTables.dateTime.css
pkg/css/ext/datatables/dataTables.dateTime.min.css
pkg/css/ext/datatables/dataTables.min.css
pkg/css/ext/datatables/fixedColumns.bootstrap4.css
pkg/css/ext/datatables/fixedColumns.bootstrap4.min.css
pkg/css/ext/datatables/fixedHeader.bootstrap4.css
pkg/css/ext/datatables/fixedHeader.bootstrap4.min.css
pkg/css/ext/datatables/keyTable.bootstrap4.css
pkg/css/ext/datatables/keyTable.bootstrap4.min.css
pkg/css/ext/datatables/responsive.bootstrap4.css
pkg/css/ext/datatables/responsive.bootstrap4.min.css
pkg/css/ext/datatables/rowGroup.bootstrap4.css
src/myams_js.egg-info/PKG-INFO
src/myams_js.egg-info/SOURCES.txt
src/myams_js.egg-info/dependency_links.txt
src/myams_js.egg-info/entry_points.txt
src/myams_js.egg-info/namespace_packages.txt
src/myams_js.egg-info/not-zip-safe
src/myams_js.egg-info/requires.txt
src/myams_js.egg-info/top_level.txt
