Metadata-Version: 2.1
Name: myams-js
Version: 2.9.5
Summary: MyAMS.js extension framework
Home-page: https://pyams.readthedocs.io
Author: Thierry Florac
Author-email: tflorac@ulthar.net
License: ZPL
Keywords: Pyramid PyAMS
Classifier: License :: OSI Approved :: Zope Public License
Classifier: Development Status :: 4 - Beta
Classifier: Programming Language :: Python
Classifier: Framework :: Pyramid
Classifier: Topic :: Software Development :: Libraries :: Python Modules
Requires-Python: >=3.7
Provides-Extra: test
License-File: LICENSE
